pymatroh/__init__.py
pymatroh/__main__.py
pymatroh-0.0.2.dist-info/LICENSE
pymatroh-0.0.2.dist-info/METADATA
pymatroh-0.0.2.dist-info/WHEEL
pymatroh-0.0.2.dist-info/top_level.txt
pymatroh-0.0.2.dist-info/RECORD
