Metadata-Version: 2.2
Name: pymatroh
Version: 0.0.2
Summary: A python module to create random matrices.
Author: IT-Administrators
Maintainer: IT-Administrators
License: MIT License
Project-URL: Homepage, https://github.com/IT-Administrators/pymatroh
Keywords: matrix,random,int,integer,float,complex,binary
Classifier: Programming Language :: Python :: 3
Classifier: License :: OSI Approved :: MIT License
Classifier: Operating System :: OS Independent
Requires-Python: >=3.7
License-File: LICENSE
